README.md
setup.py
pyinsar/__init__.py
pyinsar.egg-info/PKG-INFO
pyinsar.egg-info/SOURCES.txt
pyinsar.egg-info/dependency_links.txt
pyinsar.egg-info/requires.txt
pyinsar.egg-info/top_level.txt
pyinsar/data_import/__init__.py
pyinsar/data_import/import_georaster.py
pyinsar/data_import/import_raster.py
pyinsar/data_import/import_srcmod.py
pyinsar/data_import/import_utils.py
pyinsar/data_import/sentinel.py
pyinsar/data_import/uavsar.py
pyinsar/docs/pyinsar_doxygen.pdf
pyinsar/license/LICENSE
pyinsar/output/__init__.py
pyinsar/output/export_georaster.py
pyinsar/output/plot_raster.py
pyinsar/processing/__init__.py
pyinsar/processing/corrections/__init__.py
pyinsar/processing/corrections/topography.py
pyinsar/processing/corrections/troposphere.py
pyinsar/processing/data_fetcher/__init__.py
pyinsar/processing/data_fetcher/gdal.py
pyinsar/processing/data_fetcher/hdf_retriever.py
pyinsar/processing/data_fetcher/okada.py
pyinsar/processing/deformation/__init__.py
pyinsar/processing/deformation/elastic_halfspace/__init__.py
pyinsar/processing/deformation/elastic_halfspace/fault.py
pyinsar/processing/deformation/elastic_halfspace/mogi.py
pyinsar/processing/deformation/elastic_halfspace/okada.py
pyinsar/processing/deformation/elastic_halfspace/pipe.py
pyinsar/processing/deformation/elastic_halfspace/surface_load.py
pyinsar/processing/discovery/__init__.py
pyinsar/processing/discovery/classify_cnn.py
pyinsar/processing/discovery/coherence.py
pyinsar/processing/discovery/coregister.py
pyinsar/processing/discovery/deburst.py
pyinsar/processing/discovery/deformation_to_phase.py
pyinsar/processing/discovery/flat_earth.py
pyinsar/processing/discovery/interferogram.py
pyinsar/processing/discovery/los_deformation.py
pyinsar/processing/discovery/rotate_squares.py
pyinsar/processing/discovery/shown_cnn_classes.py
pyinsar/processing/discovery/temporal_decorrelation.py
pyinsar/processing/discovery/train_cnn.py
pyinsar/processing/discovery/wrap_phase.py
pyinsar/processing/geography/__init__.py
pyinsar/processing/geography/coordinates.py
pyinsar/processing/geography/geodesy.py
pyinsar/processing/geography/geomorphometry.py
