Metadata-Version: 2.1
Name: pyinsar
Version: 0.0.4
Summary: Package of InSAR utilities
Home-page: UNKNOWN
Author: MITHAGI
Author-email: skdaccess@mit.edu
License: UNKNOWN
Platform: UNKNOWN
Classifier: Topic :: Scientific/Engineering
Classifier: Intended Audience :: Science/Research
Classifier: License :: OSI Approved :: MIT License
Classifier: Programming Language :: Python :: 3 :: Only
Requires-Python: >=3.4
